{"id":"163735","media_id":"933641","title":{"english":"[Soramune (Yuzu Ramune)] Hentai Roshutsu Shimai  [Chinese] [\u6c92\u6709\u6f22\u5316] [Digital]","japanese":"[\u305d\u3089\u3080\u306d (\u67da\u5b50\u30e9\u30e0\u30cd)] \u3078\u3093\u305f\u3044\u9732\u51fa\u59c9\u59b9 [\u4e2d\u56fd\u7ffb\u8a33] [DL\u7248]","pretty":"Hentai Roshutsu Shimai"},"images":{"pages":[{"t":"j","w":1280,"h":1798},{"t":"j","w":1200,"h":1685},{"t":"j","w":1280,"h":1807},{"t":"j","w":1280,"h":1807},{"t":"j","w":1280,"h":1807},{"t":"j","w":1280,"h":1807},{"t":"j","w":1280,"h":1807},{"t":"j","w":1280,"h":1807},{"t":"j","w":1280,"h":1807},{"t":"j","w":1280,"h":1807},{"t":"j","w":1280,"h":1807},{"t":"j","w":1280,"h":1807},{"t":"j","w":1280,"h":1807},{"t":"j","w":1280,"h":1807},{"t":"j","w":1280,"h":1807},{"t":"j","w":1280,"h":1807},{"t":"j","w":1280,"h":1807},{"t":"j","w":1280,"h":1807},{"t":"j","w":1280,"h":1807},{"t":"j","w":1280,"h":1807},{"t":"j","w":1280,"h":1807},{"t":"j","w":1280,"h":1807},{"t":"j","w":1280,"h":1807},{"t":"j","w":1280,"h":1807},{"t":"j","w":1280,"h":1807},{"t":"j","w":1280,"h":1807},{"t":"j","w":1280,"h":1807},{"t":"j","w":1280,"h":1807},{"t":"j","w":1280,"h":1807},{"t":"j","w":1280,"h":1807},{"t":"j","w":1200,"h":1695}],"cover":{"t":"j","w":350,"h":492},"thumbnail":{"t":"j","w":250,"h":351}},"scanlator":"","upload_date":1463118258,"tags":[{"id":9118,"type":"group","name":"soramune","url":"/group/soramune/","count":38},{"id":19899,"type":"tag","name":"exhibitionism","url":"/tag/exhibitionism/","count":8720},{"id":8050,"type":"tag","name":"females only","url":"/tag/females-only/","count":8765},{"id":19954,"type":"tag","name":"yuri","url":"/tag/yuri/","count":20241},{"id":29963,"type":"language","name":"chinese","url":"/language/chinese/","count":44293},{"id":17249,"type":"language","name":"translated","url":"/language/translated/","count":109734},{"id":37661,"type":"artist","name":"yuzu ramune","url":"/artist/yuzu-ramune/","count":40},{"id":33172,"type":"category","name":"doujinshi","url":"/category/doujinshi/","count":228729},{"id":30206,"type":"tag","name":"tribadism","url":"/tag/tribadism/","count":1920},{"id":9162,"type":"tag","name":"masturbation","url":"/tag/masturbation/","count":9348}],"num_pages":31,"num_favorites":172}