{"id":172766,"media_id":"970346","title":{"english":"[A-office (Yumi Ichirou)] Kikan Yumi Ichirou Soushuuhen + \u03b5 (Various) [Digital]","japanese":"[A-office (\u53cb\u7f8e\u30a4\u30c1\u30ed\u30a6)] \u5b63\u520a\u53cb\u7f8e\u30a4\u30c1\u30ed\u30a6\u7dcf\u96c6\u7de8\uff0b\u03b5 (\u3088\u308d\u305a) [DL\u7248]","pretty":"Kikan Yumi Ichirou Soushuuhen + \u03b5"},"images":{"pages":[{"t":"j","w":1075,"h":1522},{"t":"p","w":1075,"h":1522},{"t":"j","w":1075,"h":1522},{"t":"j","w":1075,"h":1522},{"t":"j","w":1075,"h":1522},{"t":"j","w":1075,"h":1522},{"t":"j","w":1075,"h":1522},{"t":"j","w":1075,"h":1522},{"t":"j","w":1075,"h":1522},{"t":"j","w":1075,"h":1522},{"t":"j","w":1075,"h":1522},{"t":"j","w":1075,"h":1522},{"t":"j","w":1075,"h":1522},{"t":"j","w":1075,"h":1522},{"t":"j","w":1075,"h":1522},{"t":"j","w":1075,"h":1522},{"t":"j","w":1075,"h":1522},{"t":"j","w":1075,"h":1522},{"t":"j","w":1075,"h":1522},{"t":"j","w":1075,"h":1522},{"t":"j","w":1075,"h":1522},{"t":"j","w":1075,"h":1522},{"t":"j","w":1075,"h":1522},{"t":"j","w":1075,"h":1522},{"t":"j","w":1075,"h":1522},{"t":"j","w":1075,"h":1522},{"t":"j","w":1075,"h":1522},{"t":"j","w":1075,"h":1522},{"t":"j","w":1075,"h":1522},{"t":"j","w":1075,"h":1522},{"t":"j","w":1075,"h":1522},{"t":"j","w":1075,"h":1522},{"t":"j","w":1075,"h":1522},{"t":"j","w":1075,"h":1522},{"t":"j","w":1075,"h":1522},{"t":"j","w":1075,"h":1522},{"t":"j","w":1075,"h":1522},{"t":"j","w":1075,"h":1522},{"t":"j","w":1075,"h":1522},{"t":"j","w":1075,"h":1522},{"t":"j","w":1075,"h":1522},{"t":"j","w":1075,"h":1522},{"t":"j","w":1075,"h":1522},{"t":"j","w":1075,"h":1522},{"t":"j","w":1075,"h":1522},{"t":"j","w":1075,"h":1522},{"t":"j","w":1075,"h":1522},{"t":"j","w":1075,"h":1522},{"t":"j","w":1075,"h":1522},{"t":"j","w":1075,"h":1522},{"t":"j","w":1075,"h":1522},{"t":"j","w":1075,"h":1522},{"t":"j","w":1075,"h":1522},{"t":"j","w":1075,"h":1522},{"t":"j","w":1075,"h":1522},{"t":"j","w":1075,"h":1522},{"t":"j","w":1075,"h":1522},{"t":"j","w":1075,"h":1522},{"t":"j","w":1075,"h":1522},{"t":"j","w":1075,"h":1522},{"t":"j","w":1075,"h":1522},{"t":"j","w":1075,"h":1522},{"t":"j","w":1075,"h":1522},{"t":"j","w":1075,"h":1522},{"t":"j","w":1075,"h":1522},{"t":"j","w":1075,"h":1522},{"t":"j","w":1075,"h":1522},{"t":"j","w":1075,"h":1522},{"t":"j","w":1075,"h":1522},{"t":"j","w":1075,"h":1522},{"t":"j","w":1075,"h":1522},{"t":"j","w":1075,"h":1522},{"t":"j","w":1075,"h":1522},{"t":"j","w":1075,"h":1522},{"t":"j","w":1075,"h":1522},{"t":"j","w":1075,"h":1522},{"t":"j","w":1075,"h":1522},{"t":"j","w":1075,"h":1522},{"t":"j","w":1075,"h":1522},{"t":"j","w":1075,"h":1522},{"t":"j","w":1075,"h":1522},{"t":"j","w":1075,"h":1522},{"t":"j","w":1075,"h":1522},{"t":"j","w":1075,"h":1522},{"t":"j","w":1075,"h":1522},{"t":"p","w":1075,"h":1522},{"t":"p","w":1075,"h":1522},{"t":"j","w":1075,"h":1522}],"cover":{"t":"j","w":350,"h":496},"thumbnail":{"t":"j","w":250,"h":354}},"scanlator":"","upload_date":1472630746,"tags":[{"id":27473,"type":"tag","name":"mosaic censorship","url":"/tag/mosaic-censorship/","count":23707},{"id":8587,"type":"group","name":"a-office","url":"/group/a-office/","count":35},{"id":2937,"type":"tag","name":"big breasts","url":"/tag/big-breasts/","count":103273},{"id":25614,"type":"tag","name":"paizuri","url":"/tag/paizuri/","count":22785},{"id":27576,"type":"artist","name":"yumi ichirou","url":"/artist/yumi-ichirou/","count":122},{"id":33172,"type":"category","name":"doujinshi","url":"/category/doujinshi/","count":228729},{"id":6346,"type":"language","name":"japanese","url":"/language/japanese/","count":191613},{"id":6022,"type":"character","name":"etsuko toyohara","url":"/character/etsuko-toyohara/","count":19},{"id":13093,"type":"character","name":"cagalli yula athha","url":"/character/cagalli-yula-athha/","count":110},{"id":16159,"type":"character","name":"meer campbell","url":"/character/meer-campbell/","count":166},{"id":30218,"type":"character","name":"flay allster","url":"/character/flay-allster/","count":74},{"id":10314,"type":"tag","name":"schoolgirl uniform","url":"/tag/schoolgirl-uniform/","count":56168},{"id":7838,"type":"tag","name":"magical girl","url":"/tag/magical-girl/","count":2640},{"id":3129,"type":"parody","name":"gundam seed","url":"/parody/gundam-seed/","count":314},{"id":8741,"type":"parody","name":"super real mahjong","url":"/parody/super-real-mahjong/","count":55},{"id":947,"type":"parody","name":"gundam seed destiny","url":"/parody/gundam-seed-destiny/","count":493},{"id":27415,"type":"parody","name":"heartcatch precure","url":"/parody/heartcatch-precure/","count":321}],"num_pages":88,"num_favorites":436}