{"id":"245827","media_id":"1283324","title":{"english":"(C94) [Popochichi (Yahiro Pochi)] Kaikinbi no Tawawa III ~Maegami-chan no Shio no Milk Pai~ (Getsuyoubi no Tawawa)","japanese":"(C94) [\u307d\u307d\u3061\u3061 (\u516b\u5c0b\u307d\u3061)] \u89e3\u7981\u65e5\u306e\u305f\u308f\u308fIII\uff5e\u524d\u9aea\u3061\u3083\u3093\u306e\u30df\u30eb\u30af\u30d1\u30a4\uff5e (\u6708\u66dc\u65e5\u306e\u305f\u308f\u308f)","pretty":"Kaikinbi no Tawawa III"},"images":{"pages":[{"t":"j","w":1100,"h":1579},{"t":"j","w":1100,"h":1573},{"t":"j","w":1100,"h":1582},{"t":"j","w":1100,"h":1576},{"t":"j","w":1100,"h":1583},{"t":"j","w":1100,"h":1578},{"t":"j","w":1100,"h":1583},{"t":"j","w":1100,"h":1582},{"t":"j","w":1100,"h":1584},{"t":"j","w":1100,"h":1577},{"t":"j","w":1100,"h":1586},{"t":"j","w":1100,"h":1578},{"t":"j","w":1100,"h":1586},{"t":"j","w":1100,"h":1578},{"t":"j","w":1100,"h":1582},{"t":"j","w":1100,"h":1579},{"t":"j","w":1100,"h":1586},{"t":"j","w":1100,"h":1579},{"t":"j","w":1100,"h":1587},{"t":"j","w":1100,"h":1575},{"t":"j","w":1100,"h":1590},{"t":"j","w":1100,"h":1593},{"t":"j","w":1100,"h":1593},{"t":"j","w":1100,"h":1577},{"t":"j","w":1100,"h":1584},{"t":"j","w":1100,"h":1597}],"cover":{"t":"j","w":350,"h":502},"thumbnail":{"t":"j","w":250,"h":359}},"scanlator":"","upload_date":1536362027,"tags":[{"id":53444,"type":"parody","name":"getsuyoubi no tawawa","url":"/parody/getsuyoubi-no-tawawa/","count":115},{"id":5114,"type":"group","name":"popochichi","url":"/group/popochichi/","count":163},{"id":12,"type":"artist","name":"yahiro pochi","url":"/artist/yahiro-pochi/","count":269},{"id":2937,"type":"tag","name":"big breasts","url":"/tag/big-breasts/","count":108513},{"id":24102,"type":"tag","name":"lactation","url":"/tag/lactation/","count":12345},{"id":33172,"type":"category","name":"doujinshi","url":"/category/doujinshi/","count":238435},{"id":6346,"type":"language","name":"japanese","url":"/language/japanese/","count":197135},{"id":21572,"type":"tag","name":"multi-work series","url":"/tag/multi-work-series/","count":15196},{"id":24726,"type":"tag","name":"apron","url":"/tag/apron/","count":3027}],"num_pages":26,"num_favorites":893}