{"id":"253744","media_id":"1317867","title":{"english":"(Shotaket 8) [Saku Saku Circle (Various)] Itsumono Copy-shi","japanese":"(\u30b7\u30e7\u30bf\u30b1\u30c3\u30c88) [\u3055\u304f\u3055\u304f\u3055\uff5e\u304f\u308b (\u3088\u308d\u305a)] \u3044\u3064\u3082\u306e\u30b3\u30d4\u30fc\u8a8c","pretty":"Itsumono Copy-shi"},"images":{"pages":[{"t":"j","w":1280,"h":1811},{"t":"j","w":1280,"h":1807},{"t":"j","w":1280,"h":1806},{"t":"j","w":1280,"h":1810},{"t":"j","w":1280,"h":1822},{"t":"j","w":1280,"h":1795},{"t":"j","w":1280,"h":1807},{"t":"j","w":1280,"h":1806},{"t":"j","w":1280,"h":1807},{"t":"j","w":1280,"h":1797},{"t":"j","w":1280,"h":1801},{"t":"j","w":1280,"h":1806},{"t":"j","w":1280,"h":1805},{"t":"j","w":1280,"h":1802},{"t":"j","w":1280,"h":1802},{"t":"j","w":1280,"h":1801},{"t":"j","w":1280,"h":1812},{"t":"j","w":1280,"h":1800},{"t":"j","w":1280,"h":1816},{"t":"j","w":1280,"h":1808},{"t":"j","w":1280,"h":1813},{"t":"j","w":1280,"h":1804},{"t":"p","w":966,"h":2064}],"cover":{"t":"j","w":350,"h":495},"thumbnail":{"t":"j","w":250,"h":354}},"scanlator":"","upload_date":1542827204,"tags":[{"id":17173,"type":"group","name":"saku saku circle","url":"/group/saku-saku-circle/","count":23},{"id":12043,"type":"artist","name":"akiha chiaki","url":"/artist/akiha-chiaki/","count":20},{"id":5667,"type":"artist","name":"azuma kyouto","url":"/artist/azuma-kyouto/","count":72},{"id":9290,"type":"artist","name":"faust","url":"/artist/faust/","count":40},{"id":12047,"type":"artist","name":"macop","url":"/artist/macop/","count":64},{"id":53878,"type":"artist","name":"miyama rima","url":"/artist/miyama-rima/","count":8},{"id":15782,"type":"tag","name":"crossdressing","url":"/tag/crossdressing/","count":13036},{"id":32341,"type":"tag","name":"shotacon","url":"/tag/shotacon/","count":40094},{"id":29023,"type":"tag","name":"tomgirl","url":"/tag/tomgirl/","count":9719},{"id":23895,"type":"tag","name":"yaoi","url":"/tag/yaoi/","count":28732},{"id":27378,"type":"tag","name":"artbook","url":"/tag/artbook/","count":1831},{"id":33172,"type":"category","name":"doujinshi","url":"/category/doujinshi/","count":231184},{"id":6346,"type":"language","name":"japanese","url":"/language/japanese/","count":193003},{"id":8546,"type":"artist","name":"po-ju","url":"/artist/po-ju/","count":191},{"id":90671,"type":"parody","name":"original","url":"/parody/original/","count":20661}],"num_pages":23,"num_favorites":27}