{"id":334131,"media_id":"1765000","title":{"english":"[Sena Youtarou] Nettori Netorare Ch. 7 -Kunoichi Kureha no Baai-","japanese":"[\u702c\u5948\u967d\u592a\u90ce] \u306d\u3063\u3068\u308a\u30cd\u30c8\u30e9\u30ec \u7b2c7\u8a71\uff5e\u304f\u30ce\u4e00\u66ae\u8449\u306e\u5834\u5408\uff5e","pretty":"Nettori Netorare Ch. 7"},"images":{"pages":[{"t":"j","w":1042,"h":1500},{"t":"j","w":1042,"h":1500},{"t":"j","w":1042,"h":1500},{"t":"j","w":1042,"h":1500},{"t":"j","w":1042,"h":1500},{"t":"j","w":1042,"h":1500},{"t":"j","w":1042,"h":1500},{"t":"j","w":1042,"h":1500},{"t":"j","w":1042,"h":1500},{"t":"j","w":1042,"h":1500},{"t":"j","w":1042,"h":1500},{"t":"j","w":1042,"h":1500},{"t":"j","w":1042,"h":1500},{"t":"j","w":1042,"h":1500},{"t":"j","w":1042,"h":1500},{"t":"j","w":1042,"h":1500},{"t":"j","w":1042,"h":1500},{"t":"j","w":1042,"h":1500},{"t":"j","w":1042,"h":1500},{"t":"j","w":1042,"h":1500}],"cover":{"t":"j","w":350,"h":504},"thumbnail":{"t":"j","w":250,"h":360}},"scanlator":"","upload_date":1603916985,"tags":[{"id":12534,"type":"artist","name":"sena youtarou","url":"/artist/sena-youtarou/","count":180},{"id":73750,"type":"tag","name":"bald","url":"/tag/bald/","count":3253},{"id":19018,"type":"tag","name":"dark skin","url":"/tag/dark-skin/","count":23952},{"id":2956,"type":"tag","name":"old man","url":"/tag/old-man/","count":2618},{"id":35763,"type":"tag","name":"sole male","url":"/tag/sole-male/","count":71359},{"id":20525,"type":"tag","name":"defloration","url":"/tag/defloration/","count":25447},{"id":22079,"type":"tag","name":"drugs","url":"/tag/drugs/","count":7538},{"id":105833,"type":"tag","name":"gloves","url":"/tag/gloves/","count":3858},{"id":31337,"type":"tag","name":"kunoichi","url":"/tag/kunoichi/","count":1140},{"id":13720,"type":"tag","name":"nakadashi","url":"/tag/nakadashi/","count":49545},{"id":8653,"type":"tag","name":"netorare","url":"/tag/netorare/","count":18717},{"id":85288,"type":"tag","name":"ponytail","url":"/tag/ponytail/","count":11792},{"id":35762,"type":"tag","name":"sole female","url":"/tag/sole-female/","count":78850},{"id":24201,"type":"tag","name":"stockings","url":"/tag/stockings/","count":71416},{"id":33173,"type":"category","name":"manga","url":"/category/manga/","count":87004},{"id":6346,"type":"language","name":"japanese","url":"/language/japanese/","count":205131}],"num_pages":20,"num_favorites":1512}