{"id":351943,"media_id":"1871530","title":{"english":"[Camrism (Kito Sakeru)] Pecorine to Shota Kishi-kun (Princess Connect! Re:Dive) [Chinese] [\u6c92\u6709\u6f22\u5316]","japanese":"[\u30ab\u30e0\u30ea\u30ba\u30e0 (\u9b3c\u982d\u30b5\u30b1\u30eb)] \u30da\u30b3\u30ea\u30fc\u30cc\u3068\u30b7\u30e7\u30bf\u304d\u3057\u304f\u3093 (\u30d7\u30ea\u30f3\u30bb\u30b9\u30b3\u30cd\u30af\u30c8!Re:Dive) [\u4e2d\u56fd\u7ffb\u8a33]","pretty":"Pecorine to Shota Kishi-kun"},"images":{"pages":[{"t":"j","w":1280,"h":1821},{"t":"j","w":1280,"h":1821},{"t":"j","w":1280,"h":1865},{"t":"j","w":1280,"h":1863},{"t":"j","w":1280,"h":1862},{"t":"j","w":1280,"h":1863},{"t":"j","w":1280,"h":1864},{"t":"j","w":1280,"h":1870},{"t":"j","w":1280,"h":1870},{"t":"j","w":1280,"h":1862},{"t":"j","w":1280,"h":1866},{"t":"j","w":1280,"h":1867},{"t":"j","w":1280,"h":1863},{"t":"j","w":1280,"h":1869},{"t":"j","w":1280,"h":1866},{"t":"j","w":1280,"h":1864},{"t":"j","w":1280,"h":1868},{"t":"j","w":1280,"h":1865},{"t":"j","w":1280,"h":1868},{"t":"j","w":1280,"h":1868},{"t":"j","w":1280,"h":1860},{"t":"j","w":1280,"h":1867},{"t":"j","w":1280,"h":1863},{"t":"j","w":1280,"h":1867},{"t":"j","w":1280,"h":1862},{"t":"j","w":1280,"h":1869},{"t":"j","w":1280,"h":1867}],"cover":{"t":"j","w":350,"h":498},"thumbnail":{"t":"j","w":250,"h":356}},"scanlator":"","upload_date":1616308645,"tags":[{"id":9477,"type":"group","name":"camrism","url":"/group/camrism/","count":74},{"id":17249,"type":"language","name":"translated","url":"/language/translated/","count":138647},{"id":29963,"type":"language","name":"chinese","url":"/language/chinese/","count":61122},{"id":31601,"type":"artist","name":"kito sakeru","url":"/artist/kito-sakeru/","count":122},{"id":32341,"type":"tag","name":"shotacon","url":"/tag/shotacon/","count":45161},{"id":33172,"type":"category","name":"doujinshi","url":"/category/doujinshi/","count":265048},{"id":35762,"type":"tag","name":"sole female","url":"/tag/sole-female/","count":85705},{"id":35763,"type":"tag","name":"sole male","url":"/tag/sole-male/","count":77466},{"id":91195,"type":"parody","name":"princess connect","url":"/parody/princess-connect/","count":705},{"id":106373,"type":"character","name":"pecorine","url":"/character/pecorine/","count":115}],"num_pages":27,"num_favorites":1499}