{"id":"361914","media_id":"1927923","title":{"english":"(COMIC1 BS-sai Special) [Shironegiya (miya9)] Hakase no Yoru no Joshu. Soushuuhen (Pok\u00e9mon Sun and Moon)","japanese":"(COMIC1 BS\u796d \u30b9\u30da\u30b7\u30e3\u30eb) [\u767d\u30cd\u30ae\u5c4b (miya9)] \u535a\u58eb\u306e\u591c\u306e\u52a9\u624b\u3002 \u7dcf\u96c6\u7de8 (\u30dd\u30b1\u30c3\u30c8\u30e2\u30f3\u30b9\u30bf\u30fc \u30b5\u30f3\u30fb\u30e0\u30fc\u30f3)","pretty":"Hakase no Yoru no Joshu. Soushuuhen"},"images":{"pages":[{"t":"j","w":1280,"h":1823},{"t":"j","w":1280,"h":1869},{"t":"j","w":1280,"h":1867},{"t":"j","w":1280,"h":1860},{"t":"j","w":1280,"h":1862},{"t":"j","w":1280,"h":1863},{"t":"j","w":1280,"h":1859},{"t":"j","w":1280,"h":1858},{"t":"j","w":1280,"h":1866},{"t":"j","w":1280,"h":1866},{"t":"j","w":1280,"h":1863},{"t":"j","w":1280,"h":1862},{"t":"j","w":1280,"h":1865},{"t":"j","w":1280,"h":1867},{"t":"j","w":1280,"h":1868},{"t":"j","w":1280,"h":1864},{"t":"j","w":1280,"h":1868},{"t":"j","w":1280,"h":1867},{"t":"j","w":1280,"h":1869},{"t":"j","w":1280,"h":1862},{"t":"j","w":1280,"h":1869},{"t":"j","w":1280,"h":1864},{"t":"j","w":1280,"h":1869},{"t":"j","w":1280,"h":1864},{"t":"j","w":1280,"h":1865},{"t":"j","w":1280,"h":1874},{"t":"j","w":1280,"h":1866},{"t":"j","w":1280,"h":1868},{"t":"j","w":1280,"h":1874},{"t":"j","w":1280,"h":1869},{"t":"j","w":1280,"h":1867},{"t":"j","w":1280,"h":1866},{"t":"j","w":1280,"h":1872},{"t":"j","w":1280,"h":1870},{"t":"j","w":1280,"h":1876},{"t":"j","w":1280,"h":1875},{"t":"j","w":1280,"h":1875},{"t":"j","w":1280,"h":1876},{"t":"j","w":1280,"h":1871},{"t":"j","w":1280,"h":1869},{"t":"j","w":1280,"h":1870},{"t":"j","w":1280,"h":1861},{"t":"j","w":1280,"h":1865},{"t":"j","w":1280,"h":1860},{"t":"j","w":1280,"h":1864},{"t":"j","w":1280,"h":1862},{"t":"j","w":1280,"h":1860},{"t":"j","w":1280,"h":1860},{"t":"j","w":1280,"h":1867},{"t":"j","w":1280,"h":1872},{"t":"j","w":1280,"h":1873},{"t":"j","w":1280,"h":1869},{"t":"j","w":1280,"h":1864},{"t":"j","w":1280,"h":1862},{"t":"j","w":1280,"h":1864},{"t":"j","w":1280,"h":1861},{"t":"j","w":1280,"h":1864},{"t":"j","w":1280,"h":1866},{"t":"j","w":1280,"h":1864},{"t":"j","w":1280,"h":1862},{"t":"j","w":1280,"h":1862},{"t":"j","w":1280,"h":1859},{"t":"j","w":1280,"h":1863},{"t":"j","w":1280,"h":1867},{"t":"j","w":1280,"h":1859},{"t":"j","w":1280,"h":1860},{"t":"j","w":1280,"h":1862},{"t":"j","w":1280,"h":1858},{"t":"j","w":1280,"h":1860},{"t":"j","w":1280,"h":1868},{"t":"j","w":1280,"h":1870},{"t":"j","w":1280,"h":1863},{"t":"j","w":1280,"h":1865},{"t":"j","w":1280,"h":1862},{"t":"j","w":1280,"h":1863},{"t":"j","w":1280,"h":1866},{"t":"j","w":1280,"h":1870},{"t":"j","w":1280,"h":1862},{"t":"j","w":1280,"h":1862},{"t":"j","w":1280,"h":1866},{"t":"j","w":1280,"h":1868},{"t":"j","w":1280,"h":1861},{"t":"j","w":1280,"h":1867},{"t":"j","w":1280,"h":1867},{"t":"j","w":1280,"h":1869},{"t":"j","w":1280,"h":1860},{"t":"j","w":1280,"h":1863},{"t":"j","w":1280,"h":1858},{"t":"j","w":1280,"h":1859},{"t":"j","w":1280,"h":1861},{"t":"j","w":1280,"h":1864},{"t":"j","w":1280,"h":1880},{"t":"j","w":1280,"h":1879},{"t":"j","w":1280,"h":1877}],"cover":{"t":"j","w":350,"h":498},"thumbnail":{"t":"j","w":250,"h":356}},"scanlator":"","upload_date":1622999706,"tags":[{"id":6346,"type":"language","name":"japanese","url":"/language/japanese/","count":215473},{"id":8653,"type":"tag","name":"netorare","url":"/tag/netorare/","count":20653},{"id":9260,"type":"tag","name":"cheating","url":"/tag/cheating/","count":15449},{"id":11219,"type":"parody","name":"pokemon","url":"/parody/pokemon/","count":1793},{"id":14283,"type":"tag","name":"anal","url":"/tag/anal/","count":76641},{"id":19018,"type":"tag","name":"dark skin","url":"/tag/dark-skin/","count":26278},{"id":19440,"type":"tag","name":"lolicon","url":"/tag/lolicon/","count":78596},{"id":19975,"type":"artist","name":"miya9","url":"/artist/miya9/","count":98},{"id":28854,"type":"group","name":"shironegiya","url":"/group/shironegiya/","count":96},{"id":30895,"type":"tag","name":"sunglasses","url":"/tag/sunglasses/","count":1120},{"id":33172,"type":"category","name":"doujinshi","url":"/category/doujinshi/","count":271177},{"id":52759,"type":"character","name":"lillie","url":"/character/lillie/","count":183},{"id":94791,"type":"character","name":"professor kukui","url":"/character/professor-kukui/","count":15},{"id":107503,"type":"tag","name":"soushuuhen","url":"/tag/soushuuhen/","count":587},{"id":107705,"type":"tag","name":"facial hair","url":"/tag/facial-hair/","count":1692}],"num_pages":94,"num_favorites":3383}