{"id":389770,"media_id":"2125655","title":{"english":"Fire Emblem Pixiv Images (updated)","japanese":"","pretty":"Fire Emblem Pixiv Images"},"images":{"pages":[{"t":"j","w":1280,"h":1412},{"t":"j","w":1280,"h":1412},{"t":"j","w":1224,"h":1500},{"t":"j","w":1224,"h":1500},{"t":"j","w":1224,"h":1500},{"t":"j","w":1224,"h":1500},{"t":"j","w":1280,"h":548},{"t":"j","w":1280,"h":1280},{"t":"j","w":1280,"h":1280},{"t":"j","w":1280,"h":1280},{"t":"j","w":1280,"h":1280},{"t":"j","w":922,"h":1500},{"t":"j","w":922,"h":1500},{"t":"j","w":922,"h":1500},{"t":"j","w":1149,"h":1500},{"t":"j","w":1149,"h":1500},{"t":"j","w":1149,"h":1500},{"t":"j","w":1149,"h":1500},{"t":"j","w":1149,"h":1500},{"t":"j","w":1149,"h":1500},{"t":"j","w":1149,"h":1500},{"t":"j","w":1149,"h":1500},{"t":"j","w":1276,"h":1500},{"t":"j","w":1276,"h":1500},{"t":"j","w":1276,"h":1500},{"t":"j","w":1276,"h":1500},{"t":"j","w":1050,"h":1500},{"t":"j","w":1050,"h":1500},{"t":"j","w":1050,"h":1500},{"t":"j","w":1050,"h":1500},{"t":"j","w":1050,"h":1500},{"t":"j","w":1050,"h":1500},{"t":"j","w":1280,"h":1493},{"t":"j","w":1280,"h":1428},{"t":"j","w":1280,"h":1280},{"t":"j","w":1280,"h":1280},{"t":"j","w":1280,"h":1280},{"t":"j","w":1280,"h":1611},{"t":"j","w":1280,"h":1611},{"t":"j","w":1280,"h":1611},{"t":"j","w":1280,"h":1054},{"t":"j","w":1280,"h":1054},{"t":"j","w":1280,"h":1054},{"t":"j","w":1280,"h":1054},{"t":"j","w":1280,"h":1054},{"t":"j","w":1280,"h":1054}],"cover":{"t":"j","w":350,"h":386},"thumbnail":{"t":"j","w":250,"h":276}},"scanlator":"","upload_date":1643401647,"tags":[{"id":6346,"type":"language","name":"japanese","url":"/language/japanese/","count":226084},{"id":21972,"type":"parody","name":"fire emblem","url":"/parody/fire-emblem/","count":86},{"id":27473,"type":"tag","name":"mosaic censorship","url":"/tag/mosaic-censorship/","count":34499},{"id":33172,"type":"category","name":"doujinshi","url":"/category/doujinshi/","count":291588}],"num_pages":46,"num_favorites":206}