{"id":393803,"media_id":"2153204","title":{"english":"[Tokiwa Midori] Kanpai! Tsuyotsuyo Onee-chan | Utter Defeat! The Mighty Onee-chan (COMIC ExE 33) [English] [Nisor] [Digital]","japanese":"[\u5e38\u78d0\u7dd1] \u5b8c\u30d1\u30a4!\u3064\u3088\u3064\u3088\u304a\u59c9\u3061\u3083\u3093 (\u30b3\u30df\u30c3\u30af \u30a8\u30b0\u30bc 33) [\u82f1\u8a33] [DL\u7248]","pretty":"Kanpai! Tsuyotsuyo Oneechan"},"images":{"pages":[{"t":"j","w":1062,"h":1500},{"t":"j","w":1062,"h":1500},{"t":"j","w":1062,"h":1500},{"t":"j","w":1062,"h":1500},{"t":"j","w":1062,"h":1500},{"t":"j","w":1062,"h":1500},{"t":"j","w":1062,"h":1500},{"t":"j","w":1062,"h":1500},{"t":"j","w":1062,"h":1500},{"t":"j","w":1062,"h":1500},{"t":"j","w":1062,"h":1500},{"t":"j","w":1062,"h":1500},{"t":"j","w":1062,"h":1500},{"t":"j","w":1062,"h":1500},{"t":"j","w":1062,"h":1500},{"t":"j","w":1062,"h":1500},{"t":"j","w":1062,"h":1500},{"t":"j","w":1062,"h":1500},{"t":"j","w":1062,"h":1500},{"t":"j","w":1062,"h":1500},{"t":"j","w":1062,"h":1500},{"t":"j","w":1062,"h":1500},{"t":"j","w":1062,"h":1500},{"t":"j","w":1062,"h":1500},{"t":"p","w":1000,"h":700}],"cover":{"t":"j","w":350,"h":494},"thumbnail":{"t":"j","w":250,"h":353}},"scanlator":"","upload_date":1645940442,"tags":[{"id":2937,"type":"tag","name":"big breasts","url":"/tag/big-breasts/","count":130720},{"id":5452,"type":"tag","name":"gymshorts","url":"/tag/gymshorts/","count":421},{"id":9287,"type":"artist","name":"tokiwa midori","url":"/artist/tokiwa-midori/","count":95},{"id":12227,"type":"language","name":"english","url":"/language/english/","count":91225},{"id":16828,"type":"tag","name":"hairy","url":"/tag/hairy/","count":14352},{"id":17249,"type":"language","name":"translated","url":"/language/translated/","count":153609},{"id":29859,"type":"tag","name":"blowjob","url":"/tag/blowjob/","count":52394},{"id":30473,"type":"tag","name":"muscle","url":"/tag/muscle/","count":13609},{"id":30555,"type":"tag","name":"big penis","url":"/tag/big-penis/","count":14132},{"id":33173,"type":"category","name":"manga","url":"/category/manga/","count":96894},{"id":35762,"type":"tag","name":"sole female","url":"/tag/sole-female/","count":97250},{"id":35763,"type":"tag","name":"sole male","url":"/tag/sole-male/","count":86990}],"num_pages":25,"num_favorites":36814}