{"id":397713,"media_id":"2181718","title":{"english":"[Sevengar] Zoku Zoku Anoko no Chikubi wa Kaihatsu Zumi","japanese":"[\u305b\u3076\u3093\u304c\u30fc] \u7d9a\u7d9a\u3042\u306e\u5b50\u306e\u4e73\u9996\u306f\u958b\u767a\u6e08","pretty":"Zoku Zoku Anoko no Chikubi wa Kaihatsu Zumi"},"images":{"pages":[{"t":"j","w":1280,"h":1813},{"t":"j","w":1280,"h":1813},{"t":"j","w":1280,"h":1813},{"t":"j","w":1280,"h":1813},{"t":"j","w":1280,"h":1813},{"t":"j","w":1280,"h":1813},{"t":"j","w":1280,"h":1813},{"t":"j","w":1280,"h":1813},{"t":"j","w":1280,"h":1813},{"t":"j","w":1280,"h":1813},{"t":"j","w":1280,"h":1813},{"t":"j","w":1280,"h":1813},{"t":"j","w":1280,"h":1813},{"t":"j","w":1280,"h":1813},{"t":"j","w":1280,"h":1813},{"t":"j","w":1280,"h":1813},{"t":"j","w":1280,"h":1813},{"t":"j","w":1280,"h":1813},{"t":"j","w":1280,"h":1813},{"t":"j","w":1280,"h":1813},{"t":"j","w":1280,"h":1813},{"t":"j","w":1280,"h":1279}],"cover":{"t":"j","w":350,"h":496},"thumbnail":{"t":"j","w":250,"h":354}},"scanlator":"","upload_date":1648759708,"tags":[{"id":5820,"type":"tag","name":"piercing","url":"/tag/piercing/","count":7592},{"id":6346,"type":"language","name":"japanese","url":"/language/japanese/","count":226181},{"id":14971,"type":"tag","name":"sex toys","url":"/tag/sex-toys/","count":26089},{"id":33172,"type":"category","name":"doujinshi","url":"/category/doujinshi/","count":291779},{"id":35762,"type":"tag","name":"sole female","url":"/tag/sole-female/","count":98271},{"id":90671,"type":"parody","name":"original","url":"/parody/original/","count":46215},{"id":130948,"type":"artist","name":"sevengar","url":"/artist/sevengar/","count":35}],"num_pages":22,"num_favorites":1678}