{"id":398667,"media_id":"2188234","title":{"english":"[Zakizaraki] Ore ga Loli ni Hamatta Riyuu (Shougakugakusei) [Chinese]","japanese":"[\u30b6\u30ad\u30b6\u30e9\u30ad] \u4ffa\u304c\u30ed\u30ea\u306b\u30cf\u30de\u3063\u305f\u7406\u7531 (\u5c0f\u30ac\u30af\u30ac\u30af\u751f) [\u4e2d\u56fd\u7ffb\u8a33]","pretty":"Ore ga Loli ni Hamatta Riyuu"},"images":{"pages":[{"t":"j","w":1280,"h":1824},{"t":"j","w":1280,"h":1827},{"t":"j","w":1280,"h":1833},{"t":"j","w":1280,"h":1849},{"t":"j","w":1280,"h":1826},{"t":"j","w":1280,"h":1823},{"t":"j","w":1280,"h":1832},{"t":"j","w":1280,"h":1845},{"t":"j","w":1280,"h":1826},{"t":"j","w":1280,"h":1843},{"t":"j","w":1280,"h":1829},{"t":"j","w":1280,"h":1838},{"t":"j","w":1280,"h":1829},{"t":"j","w":1280,"h":1836},{"t":"j","w":1280,"h":1833},{"t":"j","w":1280,"h":1837},{"t":"j","w":1280,"h":1825},{"t":"j","w":1280,"h":1830}],"cover":{"t":"j","w":350,"h":499},"thumbnail":{"t":"j","w":250,"h":356}},"scanlator":"","upload_date":1649405759,"tags":[{"id":8378,"type":"tag","name":"glasses","url":"/tag/glasses/","count":57593},{"id":17249,"type":"language","name":"translated","url":"/language/translated/","count":154656},{"id":19440,"type":"tag","name":"lolicon","url":"/tag/lolicon/","count":81794},{"id":26956,"type":"artist","name":"zaki zaraki","url":"/artist/zaki-zaraki/","count":169},{"id":29963,"type":"language","name":"chinese","url":"/language/chinese/","count":70226},{"id":33173,"type":"category","name":"manga","url":"/category/manga/","count":97403}],"num_pages":18,"num_favorites":194}