{"id":64687,"media_id":"401191","title":{"english":"[Sol-fa-soft] Loli no yu (Hi) Nyuutou annai","japanese":"[Sol-fa-soft] \u7089\u5229\u306e\u6e6f(\u79d8)\u5165\u6e6f\u6848\u5185","pretty":"Loli no yuNyuutou annai"},"images":{"pages":[{"t":"j","w":1200,"h":1693},{"t":"j","w":1200,"h":1694},{"t":"j","w":1200,"h":1692},{"t":"j","w":1200,"h":1696},{"t":"j","w":1200,"h":1696},{"t":"j","w":1200,"h":1700},{"t":"j","w":1200,"h":1700},{"t":"j","w":1200,"h":1701},{"t":"j","w":1200,"h":1702},{"t":"j","w":1200,"h":1702},{"t":"j","w":1200,"h":1703},{"t":"j","w":1200,"h":1700},{"t":"j","w":1200,"h":1700},{"t":"j","w":1200,"h":1699},{"t":"j","w":1200,"h":1700},{"t":"j","w":1200,"h":1700},{"t":"j","w":1200,"h":1698},{"t":"j","w":1200,"h":1696}],"cover":{"t":"j","w":350,"h":494},"thumbnail":{"t":"j","w":250,"h":353}},"scanlator":"","upload_date":1403994070,"tags":[{"id":9597,"type":"group","name":"sol-fa-soft","url":"/group/sol-fa-soft/","count":17},{"id":19440,"type":"tag","name":"lolicon","url":"/tag/lolicon/","count":70096},{"id":20905,"type":"tag","name":"full color","url":"/tag/full-color/","count":33871},{"id":6346,"type":"language","name":"japanese","url":"/language/japanese/","count":193003},{"id":33172,"type":"category","name":"doujinshi","url":"/category/doujinshi/","count":231184}],"num_pages":18,"num_favorites":195}