{"id":78963,"media_id":"515108","title":{"english":"(C78) [ciaociao (Araki Kanao)] HAPPY EDEN CUTE (Hayate no Gotoku!) [English] [desudesu]","japanese":"(C78) [ciaociao (\u3042\u3089\u304d\u304b\u306a\u304a)] HAPPY EDEN CUTE (\u30cf\u30e4\u30c6\u306e\u3054\u3068\u304f\uff01) [\u82f1\u8a33]","pretty":"HAPPY EDEN CUTE"},"images":{"pages":[{"t":"j","w":1200,"h":1695},{"t":"j","w":1200,"h":1706},{"t":"j","w":1200,"h":1713},{"t":"j","w":1200,"h":1706},{"t":"j","w":1200,"h":1713},{"t":"j","w":1200,"h":1706},{"t":"j","w":1200,"h":1713},{"t":"j","w":1200,"h":1706},{"t":"j","w":1200,"h":1713},{"t":"j","w":1200,"h":1706},{"t":"j","w":1200,"h":1713},{"t":"j","w":1200,"h":1706},{"t":"j","w":1200,"h":1713},{"t":"j","w":1200,"h":1706},{"t":"j","w":1200,"h":1713},{"t":"j","w":1200,"h":1706},{"t":"j","w":1200,"h":1713},{"t":"j","w":1200,"h":1706},{"t":"j","w":1200,"h":1714},{"t":"j","w":1200,"h":1706},{"t":"j","w":1200,"h":1713},{"t":"j","w":1200,"h":1707}],"cover":{"t":"j","w":350,"h":494},"thumbnail":{"t":"j","w":250,"h":353}},"scanlator":"","upload_date":1403996618,"tags":[{"id":2937,"type":"tag","name":"big breasts","url":"/tag/big-breasts/","count":103273},{"id":5573,"type":"group","name":"ciaociao","url":"/group/ciaociao/","count":127},{"id":10330,"type":"character","name":"hayate ayasaki","url":"/character/hayate-ayasaki/","count":127},{"id":12227,"type":"language","name":"english","url":"/language/english/","count":69378},{"id":13346,"type":"artist","name":"araki kanao","url":"/artist/araki-kanao/","count":161},{"id":15069,"type":"character","name":"athena tennousu","url":"/character/athena-tennousu/","count":39},{"id":17249,"type":"language","name":"translated","url":"/language/translated/","count":109734},{"id":27567,"type":"parody","name":"hayate no gotoku","url":"/parody/hayate-no-gotoku/","count":427},{"id":33172,"type":"category","name":"doujinshi","url":"/category/doujinshi/","count":228729}],"num_pages":22,"num_favorites":171}