{"id":10861,"media_id":"32072","title":{"english":"[Anmitsu Sou] Green Apple","japanese":"[\u3042\u3093\u307f\u3064\u8349] \u3050\u308a\u30fc\u3093\u30fb\u3042\u307d\u30fc","pretty":"Green Apple"},"images":{"pages":[{"t":"j","w":1200,"h":504},{"t":"j","w":1200,"h":980},{"t":"j","w":1200,"h":801},{"t":"j","w":1123,"h":1600},{"t":"j","w":1123,"h":1600},{"t":"j","w":1123,"h":1600},{"t":"j","w":1123,"h":1600},{"t":"j","w":1123,"h":1600},{"t":"j","w":1123,"h":1600},{"t":"j","w":1123,"h":1600},{"t":"j","w":1123,"h":1600},{"t":"j","w":1123,"h":1600},{"t":"j","w":1123,"h":1600},{"t":"j","w":1123,"h":1600},{"t":"j","w":1123,"h":1600},{"t":"j","w":1123,"h":1600},{"t":"j","w":1123,"h":1600},{"t":"j","w":1123,"h":1600},{"t":"j","w":1123,"h":1600},{"t":"j","w":1123,"h":1600},{"t":"j","w":1123,"h":1600},{"t":"j","w":1123,"h":1600},{"t":"j","w":1123,"h":1600},{"t":"j","w":1123,"h":1600},{"t":"j","w":1123,"h":1600},{"t":"j","w":1123,"h":1600},{"t":"j","w":1123,"h":1600},{"t":"j","w":1123,"h":1600},{"t":"j","w":1123,"h":1600},{"t":"j","w":1123,"h":1600},{"t":"j","w":1123,"h":1600},{"t":"j","w":1123,"h":1600},{"t":"j","w":1123,"h":1600},{"t":"j","w":1123,"h":1600},{"t":"j","w":1123,"h":1600},{"t":"j","w":1123,"h":1600},{"t":"j","w":1123,"h":1600},{"t":"j","w":1123,"h":1600},{"t":"j","w":1123,"h":1600},{"t":"j","w":1123,"h":1600},{"t":"j","w":1123,"h":1600},{"t":"j","w":1123,"h":1600},{"t":"j","w":1123,"h":1600},{"t":"j","w":1123,"h":1600},{"t":"j","w":1123,"h":1600},{"t":"j","w":1123,"h":1600},{"t":"j","w":1123,"h":1600},{"t":"j","w":1123,"h":1600},{"t":"j","w":1123,"h":1600},{"t":"j","w":1123,"h":1600},{"t":"j","w":1123,"h":1600},{"t":"j","w":1123,"h":1600},{"t":"j","w":1123,"h":1600},{"t":"j","w":1123,"h":1600},{"t":"j","w":1123,"h":1600},{"t":"j","w":1123,"h":1600},{"t":"j","w":1123,"h":1600},{"t":"j","w":1123,"h":1600},{"t":"j","w":1123,"h":1600},{"t":"j","w":1123,"h":1600},{"t":"j","w":1123,"h":1600},{"t":"j","w":1123,"h":1600},{"t":"j","w":1123,"h":1600},{"t":"j","w":1123,"h":1600},{"t":"j","w":1123,"h":1600},{"t":"j","w":1123,"h":1600},{"t":"j","w":1123,"h":1600},{"t":"j","w":1123,"h":1600},{"t":"j","w":1123,"h":1600},{"t":"j","w":1123,"h":1600},{"t":"j","w":1123,"h":1600},{"t":"j","w":1123,"h":1600},{"t":"j","w":1123,"h":1600},{"t":"j","w":1123,"h":1600},{"t":"j","w":1123,"h":1600},{"t":"j","w":1123,"h":1600},{"t":"j","w":1123,"h":1600},{"t":"j","w":1123,"h":1600},{"t":"j","w":1123,"h":1600},{"t":"j","w":1123,"h":1600},{"t":"j","w":1123,"h":1600},{"t":"j","w":1123,"h":1600},{"t":"j","w":1123,"h":1600},{"t":"j","w":1123,"h":1600},{"t":"j","w":1123,"h":1600},{"t":"j","w":1123,"h":1600},{"t":"j","w":1123,"h":1600},{"t":"j","w":1123,"h":1600},{"t":"j","w":1123,"h":1600},{"t":"j","w":1123,"h":1600},{"t":"j","w":1123,"h":1600},{"t":"j","w":1123,"h":1600},{"t":"j","w":1123,"h":1600},{"t":"j","w":1123,"h":1600},{"t":"j","w":1123,"h":1600},{"t":"j","w":1123,"h":1600},{"t":"j","w":1123,"h":1600},{"t":"j","w":1123,"h":1600},{"t":"j","w":1123,"h":1600},{"t":"j","w":1123,"h":1600},{"t":"j","w":1123,"h":1600},{"t":"j","w":1123,"h":1600},{"t":"j","w":1123,"h":1600},{"t":"j","w":1123,"h":1600},{"t":"j","w":1123,"h":1600},{"t":"j","w":1123,"h":1600},{"t":"j","w":1123,"h":1600},{"t":"j","w":1123,"h":1600},{"t":"j","w":1123,"h":1600},{"t":"j","w":1123,"h":1600},{"t":"j","w":1123,"h":1600},{"t":"j","w":1123,"h":1600},{"t":"j","w":1123,"h":1600},{"t":"j","w":1123,"h":1600},{"t":"j","w":1123,"h":1600},{"t":"j","w":1123,"h":1600},{"t":"j","w":1123,"h":1600},{"t":"j","w":1123,"h":1600},{"t":"j","w":1123,"h":1600},{"t":"j","w":1123,"h":1600},{"t":"j","w":1123,"h":1600},{"t":"j","w":1123,"h":1600},{"t":"j","w":1123,"h":1600},{"t":"j","w":1123,"h":1600},{"t":"j","w":1123,"h":1600},{"t":"j","w":1123,"h":1600},{"t":"j","w":1123,"h":1600},{"t":"j","w":1123,"h":1600},{"t":"j","w":1123,"h":1600},{"t":"j","w":1123,"h":1600},{"t":"j","w":1123,"h":1600},{"t":"j","w":1123,"h":1600},{"t":"j","w":1123,"h":1600},{"t":"j","w":1123,"h":1600},{"t":"j","w":1123,"h":1600},{"t":"j","w":1123,"h":1600},{"t":"j","w":1123,"h":1600},{"t":"j","w":1123,"h":1600},{"t":"j","w":1123,"h":1600},{"t":"j","w":1123,"h":1600},{"t":"j","w":1123,"h":1600},{"t":"j","w":1123,"h":1600},{"t":"j","w":1123,"h":1600},{"t":"j","w":1123,"h":1600},{"t":"j","w":1123,"h":1600},{"t":"j","w":1123,"h":1600},{"t":"j","w":1123,"h":1600},{"t":"j","w":1123,"h":1600},{"t":"j","w":1123,"h":1600},{"t":"j","w":1123,"h":1600},{"t":"j","w":1123,"h":1600},{"t":"j","w":1123,"h":1600},{"t":"j","w":1123,"h":1600},{"t":"j","w":1123,"h":1600},{"t":"j","w":1123,"h":1600},{"t":"j","w":1123,"h":1600},{"t":"j","w":1123,"h":1600},{"t":"j","w":1123,"h":1600},{"t":"j","w":1123,"h":1600},{"t":"j","w":1123,"h":1600},{"t":"j","w":1123,"h":1600},{"t":"j","w":1123,"h":1600},{"t":"j","w":1123,"h":1600},{"t":"j","w":1123,"h":1600},{"t":"j","w":1123,"h":1600},{"t":"j","w":1123,"h":1600},{"t":"j","w":1123,"h":1600},{"t":"j","w":1123,"h":1600},{"t":"j","w":1123,"h":1600},{"t":"j","w":1200,"h":839},{"t":"j","w":1123,"h":1600},{"t":"j","w":1200,"h":1047}],"cover":{"t":"j","w":350,"h":147},"thumbnail":{"t":"j","w":250,"h":105}},"scanlator":"","upload_date":1403982957,"tags":[{"id":8378,"type":"tag","name":"glasses","url":"/tag/glasses/","count":48712},{"id":32094,"type":"artist","name":"anmitsu sou","url":"/artist/anmitsu-sou/","count":17},{"id":6346,"type":"language","name":"japanese","url":"/language/japanese/","count":193003},{"id":33173,"type":"category","name":"manga","url":"/category/manga/","count":77855}],"num_pages":172,"num_favorites":17}