{"id":159563,"media_id":"916001","title":{"english":"(C64) [Poyopacho (UmiUshi)] Poyopacho Storm (Gad Guard)","japanese":"(C64) [\u307d\u3088\u3071\u3061\u3087 (\u3046\u307f\u3046\u3057)] Poyopacho STORM (\u30ac\u30c9\u30ac\u30fc\u30c9)","pretty":"Poyopacho Storm"},"images":{"pages":[{"t":"j","w":1067,"h":1500},{"t":"j","w":1051,"h":1500},{"t":"j","w":1066,"h":1500},{"t":"j","w":1066,"h":1500},{"t":"j","w":1051,"h":1500},{"t":"j","w":1051,"h":1500},{"t":"j","w":1051,"h":1500},{"t":"j","w":1051,"h":1500},{"t":"j","w":1053,"h":1500},{"t":"j","w":1051,"h":1500},{"t":"j","w":1051,"h":1500},{"t":"j","w":1051,"h":1500},{"t":"j","w":1051,"h":1500},{"t":"j","w":1051,"h":1500},{"t":"j","w":1051,"h":1500},{"t":"j","w":1051,"h":1500},{"t":"j","w":1051,"h":1500},{"t":"j","w":1051,"h":1500},{"t":"j","w":1051,"h":1500},{"t":"j","w":1051,"h":1500},{"t":"j","w":1051,"h":1500},{"t":"j","w":1051,"h":1500},{"t":"j","w":1051,"h":1500},{"t":"j","w":1051,"h":1500},{"t":"j","w":1051,"h":1500},{"t":"j","w":1051,"h":1500},{"t":"j","w":1051,"h":1500},{"t":"j","w":1051,"h":1500},{"t":"j","w":1051,"h":1500},{"t":"j","w":1051,"h":1500},{"t":"j","w":1051,"h":1500},{"t":"j","w":1051,"h":1500},{"t":"j","w":1051,"h":1500},{"t":"j","w":1053,"h":1500}],"cover":{"t":"j","w":350,"h":492},"thumbnail":{"t":"j","w":250,"h":351}},"scanlator":"","upload_date":1459256428,"tags":[{"id":1930,"type":"group","name":"poyopacho","url":"/group/poyopacho/","count":50},{"id":3517,"type":"artist","name":"umiushi","url":"/artist/umiushi/","count":113},{"id":21454,"type":"character","name":"arashi shinozuka","url":"/character/arashi-shinozuka/","count":51},{"id":31775,"type":"tag","name":"tentacles","url":"/tag/tentacles/","count":13276},{"id":26747,"type":"parody","name":"gad guard","url":"/parody/gad-guard/","count":62},{"id":33172,"type":"category","name":"doujinshi","url":"/category/doujinshi/","count":228729},{"id":6346,"type":"language","name":"japanese","url":"/language/japanese/","count":191613}],"num_pages":34,"num_favorites":18}