{"id":186770,"media_id":"1025010","title":{"english":"[Kika = Zaru] Ane \u2606 Fes [Digital]","japanese":"[kika=\u3056\u308b] \u3042\u306d\u2606\u30d5\u30a7\u30b9 [DL\u7248]","pretty":"Ane \u2606 Fes"},"images":{"pages":[{"t":"j","w":1054,"h":1480},{"t":"j","w":1054,"h":1480},{"t":"j","w":1054,"h":1480},{"t":"j","w":1054,"h":1480},{"t":"j","w":1054,"h":1480},{"t":"j","w":1054,"h":1480},{"t":"j","w":1054,"h":1480},{"t":"j","w":1054,"h":1480},{"t":"j","w":1054,"h":1480},{"t":"j","w":1054,"h":1480},{"t":"j","w":1054,"h":1480},{"t":"j","w":1054,"h":1480},{"t":"j","w":1054,"h":1480},{"t":"j","w":1054,"h":1480},{"t":"j","w":1054,"h":1480},{"t":"j","w":1054,"h":1480},{"t":"j","w":1054,"h":1480},{"t":"j","w":1054,"h":1480},{"t":"j","w":1054,"h":1480},{"t":"j","w":1054,"h":1480},{"t":"j","w":1054,"h":1480},{"t":"j","w":1054,"h":1480},{"t":"j","w":1054,"h":1480},{"t":"j","w":1054,"h":1480},{"t":"j","w":1054,"h":1480},{"t":"j","w":1054,"h":1480},{"t":"j","w":1054,"h":1480},{"t":"j","w":1054,"h":1480},{"t":"j","w":1054,"h":1480},{"t":"j","w":1054,"h":1480},{"t":"j","w":1054,"h":1480},{"t":"j","w":1054,"h":1480},{"t":"j","w":1054,"h":1480},{"t":"j","w":1054,"h":1480},{"t":"j","w":1054,"h":1480},{"t":"j","w":1054,"h":1480},{"t":"j","w":1054,"h":1480},{"t":"j","w":1054,"h":1480},{"t":"j","w":1054,"h":1480},{"t":"j","w":1054,"h":1480},{"t":"j","w":1054,"h":1480},{"t":"j","w":1054,"h":1480},{"t":"j","w":1054,"h":1480},{"t":"j","w":1054,"h":1480},{"t":"j","w":1054,"h":1480},{"t":"j","w":1054,"h":1480},{"t":"j","w":1054,"h":1480},{"t":"j","w":1054,"h":1480},{"t":"j","w":1054,"h":1480},{"t":"j","w":1054,"h":1480},{"t":"j","w":1054,"h":1480},{"t":"j","w":1054,"h":1480},{"t":"j","w":1054,"h":1480},{"t":"j","w":1054,"h":1480},{"t":"j","w":1054,"h":1480},{"t":"j","w":1054,"h":1480},{"t":"j","w":1054,"h":1480},{"t":"j","w":1054,"h":1480},{"t":"j","w":1054,"h":1480},{"t":"j","w":1054,"h":1480},{"t":"j","w":1054,"h":1480},{"t":"j","w":1054,"h":1480},{"t":"j","w":1054,"h":1480},{"t":"j","w":1054,"h":1480},{"t":"j","w":1054,"h":1480},{"t":"j","w":1054,"h":1480},{"t":"j","w":1054,"h":1480},{"t":"j","w":1054,"h":1480},{"t":"j","w":1054,"h":1480},{"t":"j","w":1054,"h":1480},{"t":"j","w":1054,"h":1480},{"t":"j","w":1054,"h":1480},{"t":"j","w":1054,"h":1480},{"t":"j","w":1054,"h":1480},{"t":"j","w":1054,"h":1480},{"t":"j","w":1054,"h":1480},{"t":"j","w":1054,"h":1480},{"t":"j","w":1054,"h":1480},{"t":"j","w":1054,"h":1480},{"t":"j","w":1054,"h":1480},{"t":"j","w":1054,"h":1480},{"t":"j","w":1054,"h":1480},{"t":"j","w":1054,"h":1480},{"t":"j","w":1054,"h":1480},{"t":"j","w":1054,"h":1480},{"t":"j","w":1054,"h":1480},{"t":"j","w":1054,"h":1480},{"t":"j","w":1054,"h":1480},{"t":"j","w":1054,"h":1480},{"t":"j","w":1054,"h":1480},{"t":"j","w":1054,"h":1480},{"t":"j","w":1054,"h":1480},{"t":"j","w":1054,"h":1480},{"t":"j","w":1054,"h":1480},{"t":"j","w":1054,"h":1480},{"t":"j","w":1054,"h":1480},{"t":"j","w":1054,"h":1480},{"t":"j","w":1054,"h":1480},{"t":"j","w":1054,"h":1480},{"t":"j","w":1054,"h":1480},{"t":"j","w":1054,"h":1480},{"t":"j","w":1054,"h":1480},{"t":"j","w":1054,"h":1480},{"t":"j","w":1054,"h":1480},{"t":"j","w":1054,"h":1480},{"t":"j","w":1054,"h":1480},{"t":"j","w":1054,"h":1480},{"t":"j","w":1054,"h":1480},{"t":"j","w":1054,"h":1480},{"t":"j","w":1054,"h":1480},{"t":"j","w":1054,"h":1480},{"t":"j","w":1054,"h":1480},{"t":"j","w":1054,"h":1480},{"t":"j","w":1054,"h":1480},{"t":"j","w":1054,"h":1480},{"t":"j","w":1054,"h":1480},{"t":"j","w":1054,"h":1480},{"t":"j","w":1054,"h":1480},{"t":"j","w":1054,"h":1480},{"t":"j","w":1054,"h":1480},{"t":"j","w":1054,"h":1480},{"t":"j","w":1054,"h":1480},{"t":"j","w":1054,"h":1480},{"t":"j","w":1054,"h":1480},{"t":"j","w":1054,"h":1480},{"t":"j","w":1054,"h":1480},{"t":"j","w":1054,"h":1480},{"t":"j","w":1054,"h":1480},{"t":"j","w":1054,"h":1480},{"t":"j","w":1054,"h":1480},{"t":"j","w":1054,"h":1480},{"t":"j","w":1054,"h":1480},{"t":"j","w":1054,"h":1480},{"t":"j","w":1054,"h":1480},{"t":"j","w":1054,"h":1480},{"t":"j","w":1054,"h":1480},{"t":"j","w":1054,"h":1480},{"t":"j","w":1054,"h":1480},{"t":"j","w":1054,"h":1480},{"t":"j","w":1054,"h":1480},{"t":"j","w":1054,"h":1480},{"t":"j","w":1054,"h":1480},{"t":"j","w":1054,"h":1480},{"t":"j","w":1054,"h":1480},{"t":"j","w":1054,"h":1480},{"t":"j","w":1054,"h":1480},{"t":"j","w":1054,"h":1480},{"t":"j","w":1054,"h":1480},{"t":"j","w":1054,"h":1480},{"t":"j","w":1054,"h":1480},{"t":"j","w":1054,"h":1480},{"t":"j","w":1054,"h":1480},{"t":"j","w":1054,"h":1480},{"t":"j","w":1054,"h":1480},{"t":"j","w":1054,"h":1480},{"t":"j","w":1054,"h":1480},{"t":"j","w":1054,"h":1480},{"t":"j","w":1054,"h":1480},{"t":"j","w":1054,"h":1480},{"t":"j","w":1054,"h":1480},{"t":"j","w":1054,"h":1480},{"t":"j","w":1054,"h":1480},{"t":"j","w":1054,"h":1480},{"t":"j","w":1054,"h":1480},{"t":"j","w":1054,"h":1480},{"t":"j","w":1054,"h":1480},{"t":"j","w":1054,"h":1480},{"t":"j","w":1054,"h":1480},{"t":"j","w":1054,"h":1480},{"t":"j","w":1054,"h":1480},{"t":"j","w":1054,"h":1480},{"t":"j","w":1054,"h":1480},{"t":"j","w":1054,"h":1480},{"t":"j","w":1054,"h":1480},{"t":"j","w":1054,"h":1480},{"t":"j","w":1054,"h":1480},{"t":"j","w":1054,"h":1480},{"t":"j","w":1054,"h":1480},{"t":"j","w":1054,"h":1480},{"t":"j","w":1054,"h":1480},{"t":"j","w":1054,"h":1480},{"t":"j","w":1054,"h":1480},{"t":"j","w":1054,"h":1480},{"t":"j","w":1054,"h":1480},{"t":"j","w":1054,"h":1480},{"t":"j","w":1054,"h":1480},{"t":"j","w":1054,"h":1480},{"t":"j","w":1054,"h":1480},{"t":"j","w":1054,"h":1480},{"t":"j","w":1054,"h":1480},{"t":"j","w":1054,"h":1480},{"t":"j","w":1054,"h":1480},{"t":"j","w":1054,"h":1480},{"t":"j","w":1054,"h":1480},{"t":"j","w":1054,"h":1480},{"t":"j","w":1054,"h":1480},{"t":"j","w":1054,"h":1480},{"t":"j","w":1054,"h":1480},{"t":"j","w":1054,"h":1480},{"t":"j","w":1054,"h":1480},{"t":"j","w":1054,"h":1480},{"t":"j","w":1054,"h":1480},{"t":"j","w":1054,"h":1480},{"t":"j","w":1054,"h":1480},{"t":"j","w":1054,"h":1480},{"t":"j","w":1054,"h":1480}],"cover":{"t":"j","w":350,"h":491},"thumbnail":{"t":"j","w":250,"h":351}},"scanlator":"","upload_date":1486114509,"tags":[{"id":27473,"type":"tag","name":"mosaic censorship","url":"/tag/mosaic-censorship/","count":23707},{"id":23237,"type":"tag","name":"tankoubon","url":"/tag/tankoubon/","count":25051},{"id":2937,"type":"tag","name":"big breasts","url":"/tag/big-breasts/","count":103273},{"id":8378,"type":"tag","name":"glasses","url":"/tag/glasses/","count":48279},{"id":6525,"type":"tag","name":"nurse","url":"/tag/nurse/","count":3629},{"id":10314,"type":"tag","name":"schoolgirl uniform","url":"/tag/schoolgirl-uniform/","count":56168},{"id":24201,"type":"tag","name":"stockings","url":"/tag/stockings/","count":64784},{"id":2026,"type":"artist","name":"kika equals zaru","url":"/artist/kika-equals-zaru/","count":113},{"id":33173,"type":"category","name":"manga","url":"/category/manga/","count":77142},{"id":6346,"type":"language","name":"japanese","url":"/language/japanese/","count":191613}],"num_pages":206,"num_favorites":97}