{"id":201877,"media_id":"1090626","title":{"english":"(C91) [Nitousei, Veronica (ktzw, Wasabi)] Shoku ni Hakara e (My Hero Academia)","japanese":"(C91) [\u4e8c\u7b49\u661f\u3001Veronica (\u5317\u6ca2\u3001\u308f\u3055\u3073)] \u98df\u306b\u8a08\u3089\u3078 (\u50d5\u306e\u30d2\u30fc\u30ed\u30fc\u30a2\u30ab\u30c7\u30df\u30a2)","pretty":"Shoku ni Hakara e"},"images":{"pages":[{"t":"j","w":640,"h":930},{"t":"j","w":640,"h":921},{"t":"j","w":640,"h":922},{"t":"j","w":640,"h":928},{"t":"j","w":640,"h":992},{"t":"j","w":640,"h":914},{"t":"j","w":640,"h":959},{"t":"j","w":640,"h":921},{"t":"j","w":640,"h":921},{"t":"j","w":640,"h":921},{"t":"j","w":640,"h":922},{"t":"j","w":640,"h":932},{"t":"j","w":640,"h":923},{"t":"j","w":640,"h":922},{"t":"j","w":640,"h":922},{"t":"j","w":640,"h":922},{"t":"j","w":640,"h":919},{"t":"j","w":640,"h":921},{"t":"j","w":640,"h":918},{"t":"j","w":640,"h":921},{"t":"j","w":640,"h":919},{"t":"j","w":640,"h":921},{"t":"j","w":640,"h":924},{"t":"j","w":640,"h":922},{"t":"j","w":640,"h":930}],"cover":{"t":"j","w":350,"h":509},"thumbnail":{"t":"j","w":250,"h":363}},"scanlator":"","upload_date":1500923012,"tags":[{"id":29859,"type":"tag","name":"blowjob","url":"/tag/blowjob/","count":37321},{"id":21712,"type":"tag","name":"males only","url":"/tag/males-only/","count":22165},{"id":23895,"type":"tag","name":"yaoi","url":"/tag/yaoi/","count":28480},{"id":34948,"type":"character","name":"shouta aizawa","url":"/character/shouta-aizawa/","count":12},{"id":33172,"type":"category","name":"doujinshi","url":"/category/doujinshi/","count":228729},{"id":6346,"type":"language","name":"japanese","url":"/language/japanese/","count":191613},{"id":74456,"type":"character","name":"hizashi yamada","url":"/character/hizashi-yamada/","count":2},{"id":74457,"type":"group","name":"veronica","url":"/group/veronica/","count":1},{"id":74458,"type":"group","name":"nitousei","url":"/group/nitousei/","count":1},{"id":12232,"type":"parody","name":"my hero academia","url":"/parody/my-hero-academia/","count":740},{"id":74459,"type":"artist","name":"ktzw","url":"/artist/ktzw/","count":3},{"id":29106,"type":"artist","name":"wasabi","url":"/artist/wasabi/","count":17}],"num_pages":25,"num_favorites":81}