{"id":220692,"media_id":"1169678","title":{"english":"(C93) [Ichino Nijou (GeNB)] Uchi no Chaldea Seijijou (Fate/Grand Order)","japanese":"(C93) [\u3044\u3061\u306e\u306b\u3058\u3087\u3046 (GeNB)] \u3046\u3061\u306e\u30ab\u30eb\u30c7\u30a2\u6027\u4e8b\u60c5 (Fate/Grand Order)","pretty":"Uchi no Chaldea Seijijou"},"images":{"pages":[{"t":"j","w":1022,"h":1442},{"t":"j","w":1022,"h":1442},{"t":"j","w":1022,"h":1442},{"t":"j","w":1022,"h":1442},{"t":"j","w":1022,"h":1442},{"t":"j","w":1022,"h":1442},{"t":"j","w":1022,"h":1442},{"t":"j","w":1022,"h":1442},{"t":"j","w":1022,"h":1442},{"t":"j","w":1022,"h":1442},{"t":"j","w":1022,"h":1442},{"t":"j","w":1022,"h":1442},{"t":"j","w":1022,"h":1442},{"t":"j","w":1022,"h":1442},{"t":"j","w":1022,"h":1442},{"t":"j","w":1022,"h":1442},{"t":"j","w":1022,"h":1442},{"t":"j","w":1022,"h":1442},{"t":"j","w":1022,"h":1442},{"t":"j","w":1022,"h":1442},{"t":"j","w":1022,"h":1442},{"t":"j","w":1022,"h":1442},{"t":"j","w":1022,"h":1442},{"t":"j","w":1022,"h":1442},{"t":"j","w":1022,"h":1442},{"t":"j","w":1022,"h":1442},{"t":"j","w":1022,"h":1442},{"t":"j","w":1022,"h":1442}],"cover":{"t":"j","w":350,"h":494},"thumbnail":{"t":"j","w":250,"h":353}},"scanlator":"","upload_date":1515947575,"tags":[{"id":70893,"type":"group","name":"ichino nijou","url":"/group/ichino-nijou/","count":6},{"id":70894,"type":"artist","name":"genb","url":"/artist/genb/","count":6},{"id":69589,"type":"character","name":"ushiwakamaru","url":"/character/ushiwakamaru/","count":102},{"id":14283,"type":"tag","name":"anal","url":"/tag/anal/","count":65252},{"id":29859,"type":"tag","name":"blowjob","url":"/tag/blowjob/","count":37977},{"id":13720,"type":"tag","name":"nakadashi","url":"/tag/nakadashi/","count":43099},{"id":35762,"type":"tag","name":"sole female","url":"/tag/sole-female/","count":67502},{"id":35763,"type":"tag","name":"sole male","url":"/tag/sole-male/","count":61245},{"id":35605,"type":"parody","name":"fate grand order","url":"/parody/fate-grand-order/","count":8068},{"id":33172,"type":"category","name":"doujinshi","url":"/category/doujinshi/","count":231184},{"id":6346,"type":"language","name":"japanese","url":"/language/japanese/","count":193003},{"id":51810,"type":"character","name":"gudao","url":"/character/gudao/","count":3623}],"num_pages":28,"num_favorites":496}