{"id":23956,"media_id":"92270","title":{"english":"(C73) [Puni-Douraku (Kinoshita Junichi)] Puni Douraku Soushuuhen 2002-2004","japanese":"(C73) [\u3077\u306b\u9053\u697d (\u304d\u306e\u3057\u305f\u9806\u5e02)] \u3077\u306b\u9053\u697d\u7dcf\u96c6\u7de82002-2004","pretty":"Puni Douraku Soushuuhen 2002-2004"},"images":{"pages":[{"t":"j","w":1125,"h":1600},{"t":"j","w":1125,"h":1600},{"t":"j","w":1125,"h":1600},{"t":"j","w":1125,"h":1600},{"t":"j","w":1125,"h":1600},{"t":"j","w":1125,"h":1600},{"t":"j","w":1125,"h":1600},{"t":"j","w":1125,"h":1600},{"t":"j","w":1125,"h":1600},{"t":"j","w":1125,"h":1600},{"t":"j","w":1125,"h":1600},{"t":"j","w":1125,"h":1600},{"t":"j","w":1125,"h":1600},{"t":"j","w":1125,"h":1600},{"t":"j","w":1125,"h":1600},{"t":"j","w":1125,"h":1600},{"t":"j","w":1125,"h":1600},{"t":"j","w":1125,"h":1600},{"t":"j","w":1125,"h":1600},{"t":"j","w":1125,"h":1600},{"t":"j","w":1125,"h":1600},{"t":"j","w":1125,"h":1600},{"t":"j","w":1125,"h":1600},{"t":"j","w":1125,"h":1600},{"t":"j","w":1125,"h":1600},{"t":"j","w":1125,"h":1600},{"t":"j","w":1125,"h":1600},{"t":"j","w":1125,"h":1600},{"t":"j","w":1125,"h":1600},{"t":"j","w":1125,"h":1600},{"t":"j","w":1125,"h":1600},{"t":"j","w":1125,"h":1600},{"t":"j","w":1125,"h":1600},{"t":"j","w":1125,"h":1600},{"t":"j","w":1125,"h":1600},{"t":"j","w":1125,"h":1600},{"t":"j","w":1125,"h":1600},{"t":"j","w":1125,"h":1600},{"t":"j","w":1125,"h":1600},{"t":"j","w":1125,"h":1600},{"t":"j","w":1125,"h":1600},{"t":"j","w":1125,"h":1600},{"t":"j","w":1125,"h":1600},{"t":"j","w":1125,"h":1600},{"t":"j","w":1125,"h":1600},{"t":"j","w":1125,"h":1600},{"t":"j","w":1125,"h":1600},{"t":"j","w":1125,"h":1600},{"t":"j","w":1125,"h":1600},{"t":"j","w":1125,"h":1600},{"t":"j","w":1125,"h":1600},{"t":"j","w":1125,"h":1600},{"t":"j","w":1125,"h":1600},{"t":"j","w":1125,"h":1600},{"t":"j","w":1125,"h":1600},{"t":"j","w":1125,"h":1600},{"t":"j","w":1125,"h":1600},{"t":"j","w":1125,"h":1600},{"t":"j","w":1125,"h":1600},{"t":"j","w":1125,"h":1600},{"t":"j","w":1125,"h":1600},{"t":"j","w":1125,"h":1600},{"t":"j","w":1125,"h":1600},{"t":"j","w":1125,"h":1600},{"t":"j","w":1125,"h":1600},{"t":"j","w":1125,"h":1600},{"t":"j","w":1125,"h":1600},{"t":"j","w":1125,"h":1600},{"t":"j","w":1125,"h":1600},{"t":"j","w":1125,"h":1600},{"t":"j","w":1125,"h":1600},{"t":"j","w":1125,"h":1600},{"t":"j","w":1125,"h":1600},{"t":"j","w":1125,"h":1600},{"t":"j","w":1125,"h":1600},{"t":"j","w":1125,"h":1600},{"t":"j","w":1125,"h":1600},{"t":"j","w":1125,"h":1600},{"t":"j","w":1125,"h":1600},{"t":"j","w":1125,"h":1600},{"t":"j","w":1125,"h":1600},{"t":"j","w":1125,"h":1600},{"t":"j","w":1125,"h":1600},{"t":"j","w":1125,"h":1600},{"t":"j","w":1125,"h":1600},{"t":"j","w":1125,"h":1600},{"t":"j","w":1125,"h":1600},{"t":"j","w":1125,"h":1600},{"t":"j","w":1125,"h":1600},{"t":"j","w":1125,"h":1600},{"t":"j","w":1125,"h":1600},{"t":"j","w":1125,"h":1600},{"t":"j","w":1125,"h":1600},{"t":"j","w":1125,"h":1600},{"t":"j","w":1125,"h":1600},{"t":"j","w":1125,"h":1600},{"t":"j","w":1125,"h":1600},{"t":"j","w":1125,"h":1600},{"t":"j","w":1125,"h":1600},{"t":"j","w":1125,"h":1600},{"t":"j","w":1125,"h":1600},{"t":"j","w":1125,"h":1600},{"t":"j","w":1125,"h":1600},{"t":"j","w":1125,"h":1600},{"t":"j","w":1125,"h":1600},{"t":"j","w":1125,"h":1600},{"t":"j","w":1125,"h":1600},{"t":"j","w":1125,"h":1600},{"t":"j","w":1125,"h":1600},{"t":"j","w":1170,"h":1600}],"cover":{"t":"j","w":350,"h":498},"thumbnail":{"t":"j","w":250,"h":356}},"scanlator":"","upload_date":1403986220,"tags":[{"id":495,"type":"parody","name":"takamare takamaru","url":"/parody/takamare-takamaru/","count":39},{"id":2937,"type":"tag","name":"big breasts","url":"/tag/big-breasts/","count":104551},{"id":7142,"type":"tag","name":"bbw","url":"/tag/bbw/","count":4953},{"id":8010,"type":"tag","name":"group","url":"/tag/group/","count":72839},{"id":12515,"type":"group","name":"puni-douraku","url":"/group/puni-douraku/","count":28},{"id":14345,"type":"parody","name":"ojamajo doremi","url":"/parody/ojamajo-doremi/","count":525},{"id":14971,"type":"tag","name":"sex toys","url":"/tag/sex-toys/","count":21024},{"id":26819,"type":"artist","name":"kinoshita junichi","url":"/artist/kinoshita-junichi/","count":59},{"id":28550,"type":"tag","name":"teacher","url":"/tag/teacher/","count":9756},{"id":6346,"type":"language","name":"japanese","url":"/language/japanese/","count":193003},{"id":33173,"type":"category","name":"manga","url":"/category/manga/","count":77855},{"id":33172,"type":"category","name":"doujinshi","url":"/category/doujinshi/","count":231184},{"id":31879,"type":"character","name":"yukie kouchi","url":"/character/yukie-kouchi/","count":15},{"id":10314,"type":"tag","name":"schoolgirl uniform","url":"/tag/schoolgirl-uniform/","count":56614},{"id":30473,"type":"tag","name":"muscle","url":"/tag/muscle/","count":9406},{"id":19018,"type":"tag","name":"dark skin","url":"/tag/dark-skin/","count":21351}],"num_pages":110,"num_favorites":37}