{"id":29937,"media_id":"125998","title":{"english":"(COMIC1) [Mushimusume Aikoukai (ASTROGUYII)] Kira Kira Heart (Arcana Heart)","japanese":"(COMIC1) [\u87f2\u5a18\u611b\u597d\u4f1a (ASTROGUYII)] KIRA KIRA HEART! (\u30a2\u30eb\u30ab\u30ca\u30cf\u30fc\u30c8)","pretty":"Kira Kira Heart"},"images":{"pages":[{"t":"j","w":643,"h":900},{"t":"j","w":640,"h":900},{"t":"j","w":640,"h":900},{"t":"j","w":640,"h":900},{"t":"j","w":639,"h":900},{"t":"j","w":640,"h":900},{"t":"j","w":640,"h":900},{"t":"j","w":640,"h":900},{"t":"j","w":640,"h":900},{"t":"j","w":640,"h":900},{"t":"j","w":640,"h":900},{"t":"j","w":640,"h":900},{"t":"j","w":640,"h":900},{"t":"j","w":640,"h":900},{"t":"j","w":639,"h":900},{"t":"j","w":640,"h":900},{"t":"j","w":640,"h":900},{"t":"j","w":640,"h":900},{"t":"j","w":639,"h":900},{"t":"j","w":640,"h":900},{"t":"j","w":639,"h":900},{"t":"j","w":639,"h":900},{"t":"j","w":640,"h":900},{"t":"j","w":640,"h":900},{"t":"j","w":640,"h":900},{"t":"j","w":640,"h":900},{"t":"j","w":640,"h":900},{"t":"j","w":640,"h":900},{"t":"j","w":636,"h":900}],"cover":{"t":"j","w":350,"h":490},"thumbnail":{"t":"j","w":250,"h":350}},"scanlator":"","upload_date":1403987682,"tags":[{"id":425,"type":"parody","name":"arcana heart","url":"/parody/arcana-heart/","count":115},{"id":779,"type":"tag","name":"futanari","url":"/tag/futanari/","count":23173},{"id":952,"type":"artist","name":"astroguy2","url":"/artist/astroguy2/","count":61},{"id":1352,"type":"tag","name":"slime","url":"/tag/slime/","count":679},{"id":3735,"type":"tag","name":"swimsuit","url":"/tag/swimsuit/","count":19363},{"id":10603,"type":"character","name":"kira daidohji","url":"/character/kira-daidohji/","count":13},{"id":19380,"type":"group","name":"mushimusume aikoukai","url":"/group/mushimusume-aikoukai/","count":50},{"id":20282,"type":"tag","name":"footjob","url":"/tag/footjob/","count":9366},{"id":24102,"type":"tag","name":"lactation","url":"/tag/lactation/","count":11973},{"id":6346,"type":"language","name":"japanese","url":"/language/japanese/","count":191613},{"id":33172,"type":"category","name":"doujinshi","url":"/category/doujinshi/","count":228729},{"id":24380,"type":"tag","name":"pantyhose","url":"/tag/pantyhose/","count":14868},{"id":29565,"type":"tag","name":"school swimsuit","url":"/tag/school-swimsuit/","count":3954},{"id":19440,"type":"tag","name":"lolicon","url":"/tag/lolicon/","count":69490},{"id":14283,"type":"tag","name":"anal","url":"/tag/anal/","count":64587}],"num_pages":29,"num_favorites":94}