{"id":370468,"media_id":"1992099","title":{"english":"[Fary5] \u4e09\u7396\u672c\uff082018\uff09 [Chinese]","japanese":"","pretty":"\u4e09\u7396\u672c\uff082018\uff09"},"images":{"pages":[{"t":"j","w":925,"h":1729},{"t":"j","w":991,"h":1652},{"t":"j","w":967,"h":1692},{"t":"j","w":1004,"h":1631},{"t":"j","w":970,"h":1687},{"t":"j","w":991,"h":1652},{"t":"j","w":780,"h":1161}],"cover":{"t":"j","w":350,"h":636},"thumbnail":{"t":"j","w":250,"h":454}},"scanlator":"","upload_date":1629806774,"tags":[{"id":29963,"type":"language","name":"chinese","url":"/language/chinese/","count":66807},{"id":33172,"type":"category","name":"doujinshi","url":"/category/doujinshi/","count":277851},{"id":101399,"type":"parody","name":"gotoubun no hanayome","url":"/parody/gotoubun-no-hanayome/","count":192},{"id":101639,"type":"character","name":"miku nakano","url":"/character/miku-nakano/","count":112},{"id":125084,"type":"artist","name":"farys","url":"/artist/farys/","count":2}],"num_pages":7,"num_favorites":719}