{"id":373754,"media_id":"2012273","title":{"english":"[Orikuchi] Torikotoraware | Captivity (COMIC JSCK Vol. 6 2016-09) [English] {Doujins.com}","japanese":"[\u6298\u53e3] \u865c\u56da\u308f\u308c (\u30b3\u30df\u30c3\u30af\u30b8\u30a7\u30b7\u30ab Vol.6 2016\u5e749\u6708\u53f7) [\u82f1\u8a33]","pretty":"Torikotoraware | Captivity"},"images":{"pages":[{"t":"j","w":1280,"h":1794},{"t":"j","w":1280,"h":1811},{"t":"j","w":1280,"h":1811},{"t":"j","w":1280,"h":1811},{"t":"j","w":1280,"h":1811},{"t":"j","w":1280,"h":1811},{"t":"j","w":1280,"h":1811},{"t":"j","w":1280,"h":1811},{"t":"j","w":1280,"h":1811},{"t":"j","w":1280,"h":1811},{"t":"j","w":1280,"h":1811},{"t":"j","w":1280,"h":1840},{"t":"j","w":1280,"h":1829},{"t":"j","w":1280,"h":1829},{"t":"j","w":1280,"h":1811},{"t":"j","w":1280,"h":1811},{"t":"j","w":1280,"h":1811},{"t":"j","w":1280,"h":1811},{"t":"j","w":1280,"h":1811},{"t":"j","w":1280,"h":1811},{"t":"j","w":1280,"h":1811}],"cover":{"t":"j","w":350,"h":490},"thumbnail":{"t":"j","w":250,"h":350}},"scanlator":"","upload_date":1632175058,"tags":[{"id":9083,"type":"tag","name":"big ass","url":"/tag/big-ass/","count":12730},{"id":12227,"type":"language","name":"english","url":"/language/english/","count":88934},{"id":12824,"type":"tag","name":"condom","url":"/tag/condom/","count":8049},{"id":17249,"type":"language","name":"translated","url":"/language/translated/","count":149795},{"id":27473,"type":"tag","name":"mosaic censorship","url":"/tag/mosaic-censorship/","count":32555},{"id":29182,"type":"tag","name":"blackmail","url":"/tag/blackmail/","count":6320},{"id":33173,"type":"category","name":"manga","url":"/category/manga/","count":97921},{"id":35762,"type":"tag","name":"sole female","url":"/tag/sole-female/","count":93812},{"id":35763,"type":"tag","name":"sole male","url":"/tag/sole-male/","count":84197},{"id":80853,"type":"artist","name":"orikuchi hirata","url":"/artist/orikuchi-hirata/","count":30},{"id":89056,"type":"tag","name":"hidden sex","url":"/tag/hidden-sex/","count":1717}],"num_pages":21,"num_favorites":2744}