{"id":409352,"media_id":"2262372","title":{"english":"[Ahemaru] Baito Ganbaru Cosplayer-san | A Cosplayer Giving her All at a Part-Time Job (Sono Bisque Doll wa Koi o Suru) [English] [Coffedrug]","japanese":"[\u30a2\u30d8\u4e38] \u30d0\u30a4\u30c8\u304c\u3093\u3070\u308b\u30b3\u30b9\u30d7\u30ec\u30a4\u30e4\u30fc\u3055\u3093 (\u305d\u306e\u7740\u305b\u66ff\u3048\u4eba\u5f62\u306f\u604b\u3092\u3059\u308b) [\u82f1\u8a33]","pretty":"Baito Ganbaru CosplayerTime Job"},"images":{"pages":[{"t":"j","w":1280,"h":1817},{"t":"j","w":1280,"h":1817},{"t":"j","w":1280,"h":1816},{"t":"j","w":1280,"h":1816},{"t":"j","w":1280,"h":1816},{"t":"j","w":1280,"h":1816},{"t":"j","w":1280,"h":1816},{"t":"j","w":1280,"h":1816},{"t":"j","w":1280,"h":1816},{"t":"j","w":1280,"h":1816},{"t":"j","w":1280,"h":1816},{"t":"j","w":1280,"h":1816},{"t":"j","w":1280,"h":1816},{"t":"j","w":1280,"h":1816},{"t":"j","w":1280,"h":1816},{"t":"j","w":1280,"h":1816},{"t":"j","w":1280,"h":1816},{"t":"j","w":1280,"h":1816},{"t":"j","w":1280,"h":1816},{"t":"j","w":1280,"h":1816},{"t":"j","w":1280,"h":1816},{"t":"j","w":1280,"h":1816},{"t":"j","w":1280,"h":1816},{"t":"j","w":1280,"h":1816},{"t":"j","w":1280,"h":1816},{"t":"j","w":1280,"h":1816},{"t":"j","w":1280,"h":1816},{"t":"j","w":1280,"h":1816},{"t":"j","w":1280,"h":1816},{"t":"j","w":1280,"h":1816},{"t":"j","w":1280,"h":1816},{"t":"j","w":1280,"h":1816},{"t":"j","w":1280,"h":1816},{"t":"j","w":1280,"h":1816},{"t":"j","w":1280,"h":1816}],"cover":{"t":"j","w":350,"h":497},"thumbnail":{"t":"j","w":250,"h":355}},"scanlator":"","upload_date":1656795940,"tags":[{"id":683,"type":"tag","name":"squirting","url":"/tag/squirting/","count":2922},{"id":2937,"type":"tag","name":"big breasts","url":"/tag/big-breasts/","count":134257},{"id":9083,"type":"tag","name":"big ass","url":"/tag/big-ass/","count":13529},{"id":10314,"type":"tag","name":"schoolgirl uniform","url":"/tag/schoolgirl-uniform/","count":67185},{"id":12227,"type":"language","name":"english","url":"/language/english/","count":93936},{"id":12695,"type":"tag","name":"prostitution","url":"/tag/prostitution/","count":7851},{"id":13720,"type":"tag","name":"nakadashi","url":"/tag/nakadashi/","count":60118},{"id":13989,"type":"tag","name":"ahegao","url":"/tag/ahegao/","count":37838},{"id":17249,"type":"language","name":"translated","url":"/language/translated/","count":159532},{"id":19018,"type":"tag","name":"dark skin","url":"/tag/dark-skin/","count":28910},{"id":20035,"type":"tag","name":"x-ray","url":"/tag/x-ray/","count":27538},{"id":23632,"type":"tag","name":"big areolae","url":"/tag/big-areolae/","count":4959},{"id":25050,"type":"tag","name":"gyaru","url":"/tag/gyaru/","count":5280},{"id":29013,"type":"tag","name":"dilf","url":"/tag/dilf/","count":20320},{"id":31880,"type":"tag","name":"bbm","url":"/tag/bbm/","count":15938},{"id":33172,"type":"category","name":"doujinshi","url":"/category/doujinshi/","count":297707},{"id":35516,"type":"group","name":"ahemaru","url":"/group/ahemaru/","count":25},{"id":35762,"type":"tag","name":"sole female","url":"/tag/sole-female/","count":101618},{"id":35763,"type":"tag","name":"sole male","url":"/tag/sole-male/","count":90716},{"id":70083,"type":"artist","name":"ahemaru | henrik","url":"/artist/ahemaru-henrik/","count":17},{"id":127898,"type":"character","name":"marin kitagawa","url":"/character/marin-kitagawa/","count":40},{"id":138490,"type":"parody","name":"sono bisque doll wa koi o suru | my dress-up darling","url":"/parody/sono-bisque-doll-wa-koi-o-suru-my-dress-up-darling/","count":7}],"num_pages":35,"num_favorites":0}