{"id":46751,"media_id":"239764","title":{"english":"[Tsukino Jyogi] Lv69 (COMIC HOTMILK 2009-12) [English] {Yoroshii}","japanese":"[\u6708\u91ce\u5b9a\u898f] Lv69 (\u30b3\u30df\u30c3\u30af\u30db\u30c3\u30c8\u30df\u30eb\u30af 2009\u5e7412\u6708\u53f7) [\u82f1\u8a33]","pretty":"Lv69"},"images":{"pages":[{"t":"j","w":1023,"h":1505},{"t":"j","w":1020,"h":1508},{"t":"j","w":1020,"h":1504},{"t":"j","w":1019,"h":1509},{"t":"j","w":1019,"h":1503},{"t":"j","w":1016,"h":1504},{"t":"j","w":1018,"h":1504},{"t":"j","w":1015,"h":1506},{"t":"j","w":1019,"h":1504},{"t":"j","w":1013,"h":1505},{"t":"j","w":1020,"h":1505},{"t":"j","w":1030,"h":1507},{"t":"j","w":1014,"h":1504},{"t":"j","w":1026,"h":1505},{"t":"j","w":1015,"h":1502},{"t":"j","w":1021,"h":1502},{"t":"j","w":1017,"h":1505},{"t":"j","w":1023,"h":1504},{"t":"j","w":1015,"h":1501},{"t":"j","w":1018,"h":1506}],"cover":{"t":"j","w":350,"h":515},"thumbnail":{"t":"j","w":250,"h":368}},"scanlator":"","upload_date":1403990949,"tags":[{"id":1207,"type":"tag","name":"milf","url":"/tag/milf/","count":22588},{"id":2937,"type":"tag","name":"big breasts","url":"/tag/big-breasts/","count":103273},{"id":12227,"type":"language","name":"english","url":"/language/english/","count":69378},{"id":17249,"type":"language","name":"translated","url":"/language/translated/","count":109734},{"id":23285,"type":"artist","name":"tsukino jyogi","url":"/artist/tsukino-jyogi/","count":330},{"id":27384,"type":"tag","name":"mind break","url":"/tag/mind-break/","count":13136},{"id":32341,"type":"tag","name":"shotacon","url":"/tag/shotacon/","count":39737},{"id":33173,"type":"category","name":"manga","url":"/category/manga/","count":77142}],"num_pages":20,"num_favorites":1581}