{"id":64227,"media_id":"399660","title":{"english":"[Modae Shine!!!] Kusuguri Sekai Seifuku! (Street Fighter)","japanese":"[\u60b6\u3048\u6b7b\u306d!!!] \u304f\u3059\u3050\u308a\u4e16\u754c\u5f81\u670d! (\u30b9\u30c8\u30ea\u30fc\u30c8\u30d5\u30a1\u30a4\u30bf\u30fc)","pretty":"Kusuguri Sekai Seifuku!"},"images":{"pages":[{"t":"j","w":1200,"h":1697},{"t":"j","w":1200,"h":1697},{"t":"j","w":1200,"h":1697},{"t":"j","w":1200,"h":1697},{"t":"j","w":1200,"h":1697},{"t":"j","w":1200,"h":1697},{"t":"j","w":1200,"h":1697},{"t":"j","w":1200,"h":1697},{"t":"j","w":1200,"h":1697},{"t":"j","w":1200,"h":1697},{"t":"j","w":1200,"h":1697},{"t":"j","w":1200,"h":1697},{"t":"j","w":1200,"h":1697},{"t":"j","w":1200,"h":1697},{"t":"j","w":1200,"h":1697},{"t":"j","w":1200,"h":1697},{"t":"j","w":1200,"h":1697},{"t":"j","w":1200,"h":1697},{"t":"j","w":1200,"h":1697},{"t":"j","w":1200,"h":1697},{"t":"j","w":1200,"h":1697}],"cover":{"t":"j","w":350,"h":495},"thumbnail":{"t":"j","w":250,"h":354}},"scanlator":"","upload_date":1403993998,"tags":[{"id":3603,"type":"parody","name":"street fighter","url":"/parody/street-fighter/","count":1304},{"id":7684,"type":"tag","name":"armpit sex","url":"/tag/armpit-sex/","count":1076},{"id":14706,"type":"group","name":"modae shine","url":"/group/modae-shine/","count":13},{"id":15658,"type":"tag","name":"bondage","url":"/tag/bondage/","count":34540},{"id":17800,"type":"tag","name":"tickling","url":"/tag/tickling/","count":734},{"id":22975,"type":"character","name":"chun-li","url":"/character/chun-li/","count":764},{"id":6346,"type":"language","name":"japanese","url":"/language/japanese/","count":191613},{"id":33172,"type":"category","name":"doujinshi","url":"/category/doujinshi/","count":228729},{"id":32690,"type":"artist","name":"ryosuke.","url":"/artist/ryosuke/","count":11}],"num_pages":21,"num_favorites":97}