{"id":85463,"media_id":"556354","title":{"english":"(Kouroumu 8) [ROCK`inChair (Jinnai)] Deichuu no Hasu (Touhou Project)","japanese":"(\u7d05\u697c\u59228) [ROCK`inChair (\u30b8\u30f3\u30ca\u30a4)] \u6ce5\u4e2d\u4e4b\u84ee (\u6771\u65b9Project)","pretty":"Deichuu no Hasu"},"images":{"pages":[{"t":"j","w":1134,"h":1600},{"t":"p","w":1122,"h":1600},{"t":"p","w":1122,"h":1600},{"t":"p","w":1122,"h":1600},{"t":"p","w":1122,"h":1600},{"t":"p","w":1122,"h":1600},{"t":"p","w":1122,"h":1600},{"t":"p","w":1122,"h":1600},{"t":"p","w":1122,"h":1600},{"t":"p","w":1122,"h":1600},{"t":"p","w":1122,"h":1600},{"t":"p","w":1122,"h":1600},{"t":"p","w":1122,"h":1600},{"t":"p","w":1122,"h":1600},{"t":"p","w":1122,"h":1600},{"t":"p","w":1122,"h":1600},{"t":"p","w":1122,"h":1600},{"t":"p","w":1122,"h":1600},{"t":"p","w":1122,"h":1600},{"t":"p","w":1122,"h":1600},{"t":"p","w":1122,"h":1600},{"t":"p","w":1122,"h":1600},{"t":"p","w":1122,"h":1600},{"t":"j","w":1131,"h":1600}],"cover":{"t":"j","w":350,"h":494},"thumbnail":{"t":"j","w":250,"h":353}},"scanlator":"","upload_date":1403997735,"tags":[{"id":2937,"type":"tag","name":"big breasts","url":"/tag/big-breasts/","count":103273},{"id":6642,"type":"character","name":"byakuren hijiri","url":"/character/byakuren-hijiri/","count":399},{"id":8010,"type":"tag","name":"group","url":"/tag/group/","count":72150},{"id":9083,"type":"tag","name":"big ass","url":"/tag/big-ass/","count":9564},{"id":14283,"type":"tag","name":"anal","url":"/tag/anal/","count":64587},{"id":16705,"type":"group","name":"rockinchair","url":"/group/rockinchair/","count":12},{"id":18024,"type":"parody","name":"touhou project","url":"/parody/touhou-project/","count":16177},{"id":22945,"type":"tag","name":"double penetration","url":"/tag/double-penetration/","count":24472},{"id":32779,"type":"artist","name":"jinnai","url":"/artist/jinnai/","count":38},{"id":6346,"type":"language","name":"japanese","url":"/language/japanese/","count":191613},{"id":33172,"type":"category","name":"doujinshi","url":"/category/doujinshi/","count":228729}],"num_pages":24,"num_favorites":90}